dialog_reflection/__init__.py
dialog_reflection/cancelled_reason.py
dialog_reflection/lang/__init__.py
dialog_reflection/lang/ja/__init__.py
dialog_reflection/lang/ja/cancelled_reason.py
dialog_reflection/lang/ja/reflection_text_builder.py
dialog_reflection/lang/ja/reflection_text_builder_option.py
dialog_reflection/lang/ja/reflector.py
dialog_reflection/reflection_cancelled.py
dialog_reflection/reflection_text_builder.py
dialog_reflection/reflector.py
dialog_reflection-0.1.2.dist-info/LICENSE
dialog_reflection-0.1.2.dist-info/WHEEL
dialog_reflection-0.1.2.dist-info/METADATA
dialog_reflection-0.1.2.dist-info/RECORD
