Metadata-Version: 2.1
Name: dialog-reflection
Version: 0.1.2
Summary: A library for dialog systems that attempt to respond to messages as Reflective Listening.
License: GNU General Public License v3.0
Author: Sadahiro YOSHIKAWA
Requires-Python: >=3.10,<4.0
Classifier: License :: Other/Proprietary License
Classifier: Programming Language :: Python :: 3
Classifier: Programming Language :: Python :: 3.10
Requires-Dist: katsuyo-text (==0.1.2)
Requires-Dist: spacy (>=3.4.1,<4.0.0)
